setup.py
general_gaussian_and_binomial_distributions/Binomialdistribution.py
general_gaussian_and_binomial_distributions/Gaussiandistribution.py
general_gaussian_and_binomial_distributions/Generaldistribution.py
general_gaussian_and_binomial_distributions/__init__.py
general_gaussian_and_binomial_distributions.egg-info/PKG-INFO
general_gaussian_and_binomial_distributions.egg-info/SOURCES.txt
general_gaussian_and_binomial_distributions.egg-info/dependency_links.txt
general_gaussian_and_binomial_distributions.egg-info/not-zip-safe
general_gaussian_and_binomial_distributions.egg-info/top_level.txt