Metadata-Version: 1.0
Name: general-gaussian-and-binomial-distributions
Version: 0.1
Summary: Different distributions
Home-page: UNKNOWN
Author: Ashish Karn
Author-email: er.ashishkarn@gmail.com
License: UNKNOWN
Platform: UNKNOWN
